pytest_gitlab_fold/__init__.py
pytest_gitlab_fold-0.3.1.dist-info/LICENSE
pytest_gitlab_fold-0.3.1.dist-info/METADATA
pytest_gitlab_fold-0.3.1.dist-info/WHEEL
pytest_gitlab_fold-0.3.1.dist-info/entry_points.txt
pytest_gitlab_fold-0.3.1.dist-info/top_level.txt
pytest_gitlab_fold-0.3.1.dist-info/RECORD
