Metadata-Version: 2.1
Name: pytest-gitlab-fold
Version: 0.3.1
Summary: Folds output sections in GitLab CI build log
Author-email: Andreas Eisenbarth <aerilius@gmail.com>, Eldar Abusalimov <eldar.abusalimov@gmail.com>
License: MIT
Project-URL: Repository, https://github.com/aerilius/pytest-gitlab-fold
Keywords: pytest,gitlab,build,logs,continuous,integration
Classifier: Development Status :: 4 - Beta
Classifier: Framework :: Pytest
Classifier: Intended Audience :: Developers
Classifier: License :: OSI Approved :: MIT License
Classifier: Operating System :: OS Independent
Classifier: Programming Language :: Python
Classifier: Programming Language :: Python :: 3
Classifier: Programming Language :: Python :: 3.8
Classifier: Programming Language :: Python :: 3.9
Classifier: Programming Language :: Python :: 3.10
Classifier: Programming Language :: Python :: 3.11
Classifier: Programming Language :: Python :: 3.12
Classifier: Programming Language :: Python :: Implementation :: CPython
Classifier: Programming Language :: Python :: Implementation :: PyPy
Classifier: Topic :: Software Development :: Testing
Requires-Python: >=3.8
License-File: LICENSE
Requires-Dist: pytest >=2.6.0
Provides-Extra: test
Requires-Dist: pytest ; extra == 'test'
Requires-Dist: pytest-cov ; extra == 'test'
